artificer/workflows/__init__.py
artificer/workflows/features.py
artificer/workflows/operations.py
artificer/workflows/serializers.py
artificer/workflows/settings.py
artificer/workflows/store.py
artificer/workflows/types.py
artificer/workflows/workflow.py
artificer_workflows-0.1.0a18.dist-info/METADATA
artificer_workflows-0.1.0a18.dist-info/WHEEL
artificer_workflows-0.1.0a18.dist-info/licenses/LICENSE
artificer_workflows-0.1.0a18.dist-info/RECORD
