Metadata-Version: 2.4
Name: artificer-workflows
Version: 0.1.0a18
Summary: A library for developing workflow graphs that run as MCP (Model Context Protocol) servers
Author-email: scott@artificerai.dev
License: MIT
License-File: LICENSE
Keywords: ai,llm,mcp,model-context-protocol,workflow
Classifier: Development Status :: 3 - Alpha
Classifier: Intended Audience :: Developers
Classifier: License :: OSI Approved :: MIT License
Classifier: Programming Language :: Python :: 3
Classifier: Programming Language :: Python :: 3.10
Classifier: Programming Language :: Python :: 3.11
Classifier: Programming Language :: Python :: 3.12
Requires-Python: >=3.10
Requires-Dist: artificer-cli>=0.1.0a6
Requires-Dist: fastmcp>=2.0
Requires-Dist: jinja2>=3.0
Requires-Dist: pydantic>=2.12.4
Requires-Dist: questionary>=2.1.1
